{
    "fill_rate": 0,
    "grid_height": 0,
    "grid_width": 0,
    "height": 512,
    "image": "4x_1E674263_128x128.png",
    "name": "json_atlas",
    "padding_x": 0,
    "padding_y": 0,
    "pot": false,
    "regions": [
        {
            "idx": 0,
            "name": "sprite_56",
            "origin": [
                0,
                0
            ],
            "rect": [
                200,
                192,
                200,
                160
            ],
            "rotated": false
        },
        {
            "idx": 1,
            "name": "sprite_57",
            "origin": [
                0,
                0
            ],
            "rect": [
                0,
                192,
                200,
                160
            ],
            "rotated": false
        },
        {
            "idx": 2,
            "name": "sprite_58",
            "origin": [
                0,
                0
            ],
            "rect": [
                200,
                352,
                200,
                160
            ],
            "rotated": false
        },
        {
            "idx": 3,
            "name": "sprite_59",
            "origin": [
                0,
                0
            ],
            "rect": [
                0,
                352,
                200,
                160
            ],
            "rotated": false
        }
    ],
    "regions_count": 4,
    "rotations": false,
    "using_grid": false,
    "width": 512
}