{
    "fill_rate": 0,
    "grid_height": 0,
    "grid_width": 0,
    "height": 1024,
    "image": "35BE5188_1024x1024.png",
    "name": "json_atlas",
    "padding_x": 0,
    "padding_y": 0,
    "pot": false,
    "regions": [
        {
            "idx": 0,
            "name": "sprite_37",
            "origin": [
                0,
                0
            ],
            "rect": [
                420,
                604,
                420,
                420
            ],
            "rotated": false
        },
        {
            "idx": 1,
            "name": "sprite_38",
            "origin": [
                0,
                0
            ],
            "rect": [
                0,
                184,
                420,
                420
            ],
            "rotated": false
        },
        {
            "idx": 2,
            "name": "sprite_39",
            "origin": [
                0,
                0
            ],
            "rect": [
                0,
                604,
                420,
                420
            ],
            "rotated": false
        },
        {
            "idx": 3,
            "name": "sprite_40",
            "origin": [
                0,
                0
            ],
            "rect": [
                530,
                350,
                110,
                254
            ],
            "rotated": false
        },
        {
            "idx": 4,
            "name": "sprite_41",
            "origin": [
                0,
                0
            ],
            "rect": [
                420,
                350,
                110,
                254
            ],
            "rotated": false
        },
        {
            "idx": 5,
            "name": "sprite_42",
            "origin": [
                0,
                0
            ],
            "rect": [
                640,
                450,
                62,
                154
            ],
            "rotated": false
        },
        {
            "idx": 6,
            "name": "sprite_43",
            "origin": [
                0,
                0
            ],
            "rect": [
                702,
                477,
                55,
                127
            ],
            "rotated": false
        },
        {
            "idx": 7,
            "name": "sprite_44",
            "origin": [
                0,
                0
            ],
            "rect": [
                757,
                494,
                158,
                110
            ],
            "rotated": false
        },
        {
            "idx": 8,
            "name": "sprite_45",
            "origin": [
                0,
                0
            ],
            "rect": [
                840,
                914,
                150,
                110
            ],
            "rotated": false
        },
        {
            "idx": 9,
            "name": "sprite_46",
            "origin": [
                0,
                0
            ],
            "rect": [
                915,
                498,
                54,
                106
            ],
            "rotated": false
        },
        {
            "idx": 10,
            "name": "sprite_47",
            "origin": [
                0,
                0
            ],
            "rect": [
                0,
                118,
                554,
                66
            ],
            "rotated": false
        },
        {
            "idx": 11,
            "name": "sprite_48",
            "origin": [
                0,
                0
            ],
            "rect": [
                0,
                52,
                554,
                66
            ],
            "rotated": false
        },
        {
            "idx": 12,
            "name": "sprite_49",
            "origin": [
                0,
                0
            ],
            "rect": [
                554,
                118,
                394,
                66
            ],
            "rotated": false
        },
        {
            "idx": 13,
            "name": "sprite_50",
            "origin": [
                0,
                0
            ],
            "rect": [
                554,
                52,
                330,
                66
            ],
            "rotated": false
        },
        {
            "idx": 14,
            "name": "sprite_51",
            "origin": [
                0,
                0
            ],
            "rect": [
                948,
                120,
                64,
                64
            ],
            "rotated": false
        },
        {
            "idx": 15,
            "name": "sprite_52",
            "origin": [
                0,
                0
            ],
            "rect": [
                884,
                60,
                22,
                58
            ],
            "rotated": false
        },
        {
            "idx": 16,
            "name": "sprite_53",
            "origin": [
                0,
                0
            ],
            "rect": [
                1012,
                126,
                10,
                58
            ],
            "rotated": false
        },
        {
            "idx": 17,
            "name": "sprite_54",
            "origin": [
                0,
                0
            ],
            "rect": [
                0,
                2,
                390,
                50
            ],
            "rotated": false
        },
        {
            "idx": 18,
            "name": "sprite_55",
            "origin": [
                0,
                0
            ],
            "rect": [
                390,
                2,
                158,
                50
            ],
            "rotated": false
        },
        {
            "idx": 19,
            "name": "sprite_56",
            "origin": [
                0,
                0
            ],
            "rect": [
                548,
                10,
                442,
                42
            ],
            "rotated": false
        },
        {
            "idx": 20,
            "name": "sprite_57",
            "origin": [
                0,
                0
            ],
            "rect": [
                420,
                308,
                362,
                42
            ],
            "rotated": false
        },
        {
            "idx": 21,
            "name": "sprite_58",
            "origin": [
                0,
                0
            ],
            "rect": [
                782,
                316,
                190,
                34
            ],
            "rotated": false
        },
        {
            "idx": 22,
            "name": "sprite_59",
            "origin": [
                0,
                0
            ],
            "rect": [
                420,
                274,
                158,
                34
            ],
            "rotated": false
        },
        {
            "idx": 23,
            "name": "sprite_60",
            "origin": [
                0,
                0
            ],
            "rect": [
                578,
                274,
                138,
                34
            ],
            "rotated": false
        },
        {
            "idx": 24,
            "name": "sprite_61",
            "origin": [
                0,
                0
            ],
            "rect": [
                716,
                278,
                154,
                30
            ],
            "rotated": false
        },
        {
            "idx": 25,
            "name": "sprite_62",
            "origin": [
                0,
                0
            ],
            "rect": [
                990,
                26,
                26,
                26
            ],
            "rotated": false
        },
        {
            "idx": 26,
            "name": "sprite_63",
            "origin": [
                0,
                0
            ],
            "rect": [
                906,
                96,
                30,
                22
            ],
            "rotated": false
        },
        {
            "idx": 27,
            "name": "sprite_64",
            "origin": [
                0,
                0
            ],
            "rect": [
                936,
                96,
                18,
                22
            ],
            "rotated": false
        },
        {
            "idx": 28,
            "name": "sprite_65",
            "origin": [
                0,
                0
            ],
            "rect": [
                954,
                96,
                18,
                22
            ],
            "rotated": false
        },
        {
            "idx": 29,
            "name": "sprite_66",
            "origin": [
                0,
                0
            ],
            "rect": [
                972,
                96,
                18,
                22
            ],
            "rotated": false
        },
        {
            "idx": 30,
            "name": "sprite_67",
            "origin": [
                0,
                0
            ],
            "rect": [
                990,
                96,
                18,
                22
            ],
            "rotated": false
        },
        {
            "idx": 31,
            "name": "sprite_68",
            "origin": [
                0,
                0
            ],
            "rect": [
                870,
                286,
                18,
                22
            ],
            "rotated": false
        },
        {
            "idx": 32,
            "name": "sprite_69",
            "origin": [
                0,
                0
            ],
            "rect": [
                888,
                286,
                18,
                22
            ],
            "rotated": false
        },
        {
            "idx": 33,
            "name": "sprite_70",
            "origin": [
                0,
                0
            ],
            "rect": [
                906,
                286,
                18,
                22
            ],
            "rotated": false
        },
        {
            "idx": 34,
            "name": "sprite_71",
            "origin": [
                0,
                0
            ],
            "rect": [
                852,
                256,
                138,
                18
            ],
            "rotated": false
        },
        {
            "idx": 35,
            "name": "sprite_72",
            "origin": [
                0,
                0
            ],
            "rect": [
                906,
                78,
                110,
                18
            ],
            "rotated": false
        },
        {
            "idx": 36,
            "name": "sprite_73",
            "origin": [
                0,
                0
            ],
            "rect": [
                906,
                60,
                110,
                18
            ],
            "rotated": false
        },
        {
            "idx": 37,
            "name": "sprite_74",
            "origin": [
                0,
                0
            ],
            "rect": [
                420,
                238,
                110,
                18
            ],
            "rotated": false
        },
        {
            "idx": 38,
            "name": "sprite_75",
            "origin": [
                0,
                0
            ],
            "rect": [
                530,
                238,
                30,
                18
            ],
            "rotated": false
        },
        {
            "idx": 39,
            "name": "sprite_76",
            "origin": [
                0,
                0
            ],
            "rect": [
                560,
                238,
                26,
                18
            ],
            "rotated": false
        },
        {
            "idx": 40,
            "name": "sprite_77",
            "origin": [
                0,
                0
            ],
            "rect": [
                586,
                238,
                26,
                18
            ],
            "rotated": false
        },
        {
            "idx": 41,
            "name": "sprite_78",
            "origin": [
                0,
                0
            ],
            "rect": [
                1008,
                100,
                10,
                18
            ],
            "rotated": false
        },
        {
            "idx": 42,
            "name": "sprite_79",
            "origin": [
                0,
                0
            ],
            "rect": [
                742,
                242,
                130,
                14
            ],
            "rotated": false
        },
        {
            "idx": 43,
            "name": "sprite_80",
            "origin": [
                0,
                0
            ],
            "rect": [
                612,
                242,
                130,
                14
            ],
            "rotated": false
        },
        {
            "idx": 44,
            "name": "sprite_81",
            "origin": [
                0,
                0
            ],
            "rect": [
                872,
                242,
                26,
                14
            ],
            "rotated": false
        },
        {
            "idx": 45,
            "name": "sprite_82",
            "origin": [
                0,
                0
            ],
            "rect": [
                898,
                242,
                26,
                14
            ],
            "rotated": false
        },
        {
            "idx": 46,
            "name": "sprite_83",
            "origin": [
                0,
                0
            ],
            "rect": [
                924,
                242,
                26,
                14
            ],
            "rotated": false
        },
        {
            "idx": 47,
            "name": "sprite_84",
            "origin": [
                0,
                0
            ],
            "rect": [
                950,
                242,
                26,
                14
            ],
            "rotated": false
        }
    ],
    "regions_count": 48,
    "rotations": false,
    "using_grid": false,
    "width": 1024
}