{
    "fill_rate": 0,
    "grid_height": 0,
    "grid_width": 0,
    "height": 512,
    "image": "684CA7DD_512x512.png",
    "name": "json_atlas",
    "padding_x": 0,
    "padding_y": 0,
    "pot": false,
    "regions": [
        {
            "idx": 0,
            "name": "sprite_494",
            "origin": [
                0,
                0
            ],
            "rect": [
                0,
                473,
                512,
                39
            ],
            "rotated": false
        },
        {
            "idx": 1,
            "name": "sprite_495",
            "origin": [
                0,
                0
            ],
            "rect": [
                0,
                434,
                512,
                39
            ],
            "rotated": false
        },
        {
            "idx": 2,
            "name": "sprite_496",
            "origin": [
                0,
                0
            ],
            "rect": [
                0,
                395,
                512,
                39
            ],
            "rotated": false
        },
        {
            "idx": 3,
            "name": "sprite_497",
            "origin": [
                0,
                0
            ],
            "rect": [
                0,
                356,
                512,
                39
            ],
            "rotated": false
        },
        {
            "idx": 4,
            "name": "sprite_498",
            "origin": [
                0,
                0
            ],
            "rect": [
                0,
                317,
                512,
                39
            ],
            "rotated": false
        },
        {
            "idx": 5,
            "name": "sprite_499",
            "origin": [
                0,
                0
            ],
            "rect": [
                0,
                278,
                512,
                39
            ],
            "rotated": false
        },
        {
            "idx": 6,
            "name": "sprite_500",
            "origin": [
                0,
                0
            ],
            "rect": [
                0,
                239,
                512,
                39
            ],
            "rotated": false
        },
        {
            "idx": 7,
            "name": "sprite_501",
            "origin": [
                0,
                0
            ],
            "rect": [
                0,
                200,
                512,
                39
            ],
            "rotated": false
        },
        {
            "idx": 8,
            "name": "sprite_502",
            "origin": [
                0,
                0
            ],
            "rect": [
                0,
                161,
                512,
                39
            ],
            "rotated": false
        },
        {
            "idx": 9,
            "name": "sprite_503",
            "origin": [
                0,
                0
            ],
            "rect": [
                0,
                122,
                512,
                39
            ],
            "rotated": false
        },
        {
            "idx": 10,
            "name": "sprite_504",
            "origin": [
                0,
                0
            ],
            "rect": [
                0,
                83,
                512,
                39
            ],
            "rotated": false
        },
        {
            "idx": 11,
            "name": "sprite_505",
            "origin": [
                0,
                0
            ],
            "rect": [
                0,
                44,
                512,
                39
            ],
            "rotated": false
        },
        {
            "idx": 12,
            "name": "sprite_506",
            "origin": [
                0,
                0
            ],
            "rect": [
                0,
                5,
                512,
                39
            ],
            "rotated": false
        }
    ],
    "regions_count": 13,
    "rotations": false,
    "using_grid": false,
    "width": 512
}